mask2bbox/__init__.py
mask2bbox/_bboxes.py
mask2bbox/logger.py
mask2bbox/scripts/__init__.py
mask2bbox/scripts/get_average_iou.py
mask2bbox/scripts/isolate_cells.py
mask2bbox/scripts/isolate_cells_from_file.py
mask2bbox-0.0.28.dist-info/licenses/LICENSE
mask2bbox-0.0.28.dist-info/METADATA
mask2bbox-0.0.28.dist-info/WHEEL
mask2bbox-0.0.28.dist-info/entry_points.txt
mask2bbox-0.0.28.dist-info/top_level.txt
mask2bbox-0.0.28.dist-info/RECORD
