Metadata-Version: 2.4
Name: mask2bbox
Version: 0.0.28
Summary: Gets the bounding boxes from a mask file.
Author-email: "Miguel A. Ibarra-Arellano" <c180l058j@mozmail.com>
License: AGPL-3.0-or-later
Project-URL: Homepage, https://github.com/SchapiroLabor/mask2bbox
Project-URL: Issues, https://github.com/SchapiroLabor/mask2bbox/issues
Keywords: cell,mask,bounding box
Classifier: Programming Language :: Python :: 3.9
Classifier: Programming Language :: Python :: 3.10
Classifier: Programming Language :: Python :: 3.11
Classifier: Operating System :: OS Independent
Classifier: Intended Audience :: Science/Research
Classifier: License :: OSI Approved :: GNU Affero General Public License v3
Requires-Python: >=3.9
License-File: LICENSE
Requires-Dist: numpy
Requires-Dist: scikit-image
Requires-Dist: matplotlib
Dynamic: license-file
